tests/__init__.py
tests/functional/__init__.py
tests/functional/test_lite.py
tests/functional/test_s4.py
tests/unit/__init__.py
tests/unit/test_decode.py
tests/unit/test_lite.py
tests/unit/test_tion.py
tests/unit/tion.py
tion_btle/__init__.py
tion_btle/light_family.py
tion_btle/lite.py
tion_btle/s3.py
tion_btle/s4.py
tion_btle/tion.py
tion_btle-3.3.6.dist-info/LICENSE
tion_btle-3.3.6.dist-info/METADATA
tion_btle-3.3.6.dist-info/WHEEL
tion_btle-3.3.6.dist-info/top_level.txt
tion_btle-3.3.6.dist-info/RECORD
