Metadata-Version: 2.1
Name: tion-btle
Version: 3.3.6
Summary: Python module for interacting with Tion breezers
Home-page: https://github.com/TionAPI/tion_python/tree/dev
License-File: LICENSE
Requires-Dist: bleak (>=0.14.3)
